{
  "parent": "minecraft:recipes/root",
  "criteria": {
    "has_the_recipe": {
      "conditions": {
        "recipe": "minecraft:purple_trapdoor_type"
      },
      "trigger": "minecraft:recipe_unlocked"
    },
    "purple_trapdoor": {
      "conditions": {
        "items": [
          {
            "items": "minecraft:purple_dye"
          }
        ]
      },
      "trigger": "minecraft:inventory_changed"
    }
  },
  "requirements": [
    [
      "has_the_recipe",
      "purple_trapdoor"
    ]
  ],
  "rewards": {
    "recipes": [
      "minecraft:purple_trapdoor_type"
    ]
  }
}